bilibili_search_cli/__init__.py
bilibili_search_cli/cli.py
bilibili_search_cli-1.0.0.dist-info/licenses/LICENSE
bilibili_search_cli-1.0.0.dist-info/METADATA
bilibili_search_cli-1.0.0.dist-info/WHEEL
bilibili_search_cli-1.0.0.dist-info/entry_points.txt
bilibili_search_cli-1.0.0.dist-info/top_level.txt
bilibili_search_cli-1.0.0.dist-info/RECORD
